random_header_generator/__init__.py
random_header_generator/definitions.py
random_header_generator/header_generator.py
random_header_generator/utils.py
random_header_generator/data/accept.json
random_header_generator/data/acceptEncoding.json
random_header_generator/data/countries.json
random_header_generator/data/cpu_bitness.json
random_header_generator/data/header_compatibility.json
random_header_generator/data/header_order.json
random_header_generator/data/operating_systems.json
random_header_generator/data/parser_adapter.json
random_header_generator/data/safari_versions.json
random_header_generator/data/scraper_browsers.txt
random_header_generator/data/software_market_share.json
random_header_generator/data/windows_versions.json
random_header_generator/ua_generator/__init__.py
random_header_generator/ua_generator/constants.py
random_header_generator/ua_generator/generator.py
random_header_generator/ua_generator/helpers.py
random_header_generator/ua_generator/proxies.py
random_header_generator/ua_parser/__init__.py
random_header_generator/ua_parser/datatypes.py
random_header_generator/ua_parser/parser.py
random_header_generator/ua_parser/regexes.py
random_header_generator-1.2.dist-info/METADATA
random_header_generator-1.2.dist-info/WHEEL
random_header_generator-1.2.dist-info/top_level.txt
random_header_generator-1.2.dist-info/RECORD
