Metadata-Version: 2.1
Name: random-header-generator
Version: 1.2
Summary: Generator of random, realistic http headers.
Author: miltos_90
License: GNU General Public License v3.0
Keywords: python,headers,http
Classifier: Environment :: Web Environment
Classifier: Intended Audience :: Developers
Classifier: Operating System :: OS Independent
Classifier: License :: OSI Approved :: Apache Software License
Classifier: Programming Language :: Python
Classifier: Topic :: Internet :: WWW/HTTP
Classifier: Topic :: Software Development :: Libraries :: Python Modules
Classifier: Programming Language :: Python :: 3.10
Requires-Python: >=3.10
